__future__/__init__.pyi
_bleio/__init__.pyi
_eve/__init__.pyi
_pew/__init__.pyi
_pixelmap/__init__.pyi
_stage/__init__.pyi
adafruit_bus_device/__init__.pyi
adafruit_pixelbuf/__init__.pyi
aesio/__init__.pyi
alarm/__init__.pyi
analogbufio/__init__.pyi
analogio/__init__.pyi
atexit/__init__.pyi
audiobusio/__init__.pyi
audiocore/__init__.pyi
audioio/__init__.pyi
audiomixer/__init__.pyi
audiomp3/__init__.pyi
audiopwmio/__init__.pyi
bitbangio/__init__.pyi
bitmaptools/__init__.pyi
bitops/__init__.pyi
board/__init__.pyi
busio/__init__.pyi
camera/__init__.pyi
canio/__init__.pyi
countio/__init__.pyi
digitalio/__init__.pyi
displayio/__init__.pyi
dualbank/__init__.pyi
floppyio/__init__.pyi
fontio/__init__.pyi
framebufferio/__init__.pyi
frequencyio/__init__.pyi
getpass/__init__.pyi
gifio/__init__.pyi
gnss/__init__.pyi
hashlib/__init__.pyi
i2ctarget/__init__.pyi
imagecapture/__init__.pyi
ipaddress/__init__.pyi
is31fl3741/__init__.pyi
keypad/__init__.pyi
math/__init__.pyi
mdns/__init__.pyi
memorymap/__init__.pyi
memorymonitor/__init__.pyi
microcontroller/__init__.pyi
msgpack/__init__.pyi
neopixel_write/__init__.pyi
nvm/__init__.pyi
onewireio/__init__.pyi
os/__init__.pyi
paralleldisplay/__init__.pyi
ps2io/__init__.pyi
pulseio/__init__.pyi
pwmio/__init__.pyi
qrio/__init__.pyi
rainbowio/__init__.pyi
random/__init__.pyi
rgbmatrix/__init__.pyi
rotaryio/__init__.pyi
rtc/__init__.pyi
sdcardio/__init__.pyi
sdioio/__init__.pyi
sharpdisplay/__init__.pyi
socketpool/__init__.pyi
ssl/__init__.pyi
storage/__init__.pyi
struct/__init__.pyi
supervisor/__init__.pyi
synthio/__init__.pyi
terminalio/__init__.pyi
time/__init__.pyi
touchio/__init__.pyi
traceback/__init__.pyi
uheap/__init__.pyi
usb/__init__.pyi
usb_cdc/__init__.pyi
usb_hid/__init__.pyi
usb_host/__init__.pyi
usb_midi/__init__.pyi
ustack/__init__.pyi
vectorio/__init__.pyi
watchdog/__init__.pyi
wifi/__init__.pyi
zlib/__init__.pyi
types_circuitpython-8.1.0.dist-info/LICENSE
types_circuitpython-8.1.0.dist-info/METADATA
types_circuitpython-8.1.0.dist-info/WHEEL
types_circuitpython-8.1.0.dist-info/top_level.txt
types_circuitpython-8.1.0.dist-info/RECORD
