Metadata-Version: 2.1
Name: types-circuitpython
Version: 8.1.0
Summary: Type support (typings) for CircuitPython built-in binding packages.
Home-page: https://github.com/hardfury-labs/types-circuitpython
Author: HardFury
License: GNU General Public License v3 (GPLv3)
Keywords: circuitpython,micropython,adafruit
Classifier: License :: OSI Approved :: GNU General Public License v3 (GPLv3)
Classifier: Intended Audience :: Developers
Classifier: Topic :: Software Development :: Libraries
Classifier: Topic :: Software Development :: Embedded Systems
Classifier: Topic :: System :: Hardware
Classifier: Typing :: Typed
Classifier: Programming Language :: Python
Classifier: Programming Language :: Python :: 3
Classifier: Programming Language :: Python :: 3 :: Only
Classifier: Programming Language :: Python :: 3.7
Classifier: Programming Language :: Python :: 3.8
Classifier: Programming Language :: Python :: 3.9
Classifier: Programming Language :: Python :: 3.10
Requires-Python: >=3.7.0
License-File: LICENSE
Requires-Dist: adafruit-circuitpython-typing
